.gitignore
.gitreview
MANIFEST.in
setup.py
bin/swift2xtrabackup
bin/xtrabackup2swift
python_xtrabackup2swift.egg-info/PKG-INFO
python_xtrabackup2swift.egg-info/SOURCES.txt
python_xtrabackup2swift.egg-info/dependency_links.txt
python_xtrabackup2swift.egg-info/requires.txt
python_xtrabackup2swift.egg-info/top_level.txt
xtrabackup2swift/__init__.py