Metadata-Version: 1.0
Name: python-xtrabackup2swift
Version: 0.0.2
Summary: xtrabackup wrappers to store & retrieve from swift
Home-page: https://github.com/moniker-dns/python-xtrabackup2swift
Author: Simon McCartney
Author-email: simon.mccartney@hp.com
License: UNKNOWN
Platform: UNKNOWN
Classifier: Development Status :: 3 - Alpha
Classifier: License :: OSI Approved :: Apache Software License
Classifier: Operating System :: OS Independent
Classifier: Programming Language :: Python :: 2.6
Classifier: Programming Language :: Python :: 2.7
Classifier: Environment :: Console
